hspf.cp37-win_amd64.pyd
pyhspf/__init__.py
pyhspf/calibration/__init__.py
pyhspf/calibration/autocalibrator.py
pyhspf/calibration/calibratormodel.py
pyhspf/calibration/sedimentcalibrator.py
pyhspf/core/__init__.py
pyhspf/core/attributes
pyhspf/core/ftable.py
pyhspf/core/hbnreader.py
pyhspf/core/hspfmodel.py
pyhspf/core/hspfmsg.wdm
pyhspf/core/hspfplots.py
pyhspf/core/implnd.py
pyhspf/core/perlnd.py
pyhspf/core/postprocessor.py
pyhspf/core/rchres.py
pyhspf/core/specialactions.py
pyhspf/core/watershed.py
pyhspf/core/wdmutil.py
pyhspf/forecasting/NRCMhindcast.py
pyhspf/forecasting/__init__.py
pyhspf/forecasting/compare_climates.py
pyhspf/forecasting/extract_NRCM.py
pyhspf/forecasting/extract_timeseries.py
pyhspf/forecasting/forecaster.py
pyhspf/forecasting/forecastplots.py
pyhspf/forecasting/gisplots.py
pyhspf/forecasting/make_timeseries.py
pyhspf/forecasting/netcdfextractor.py
pyhspf/forecasting/nrcm.py
pyhspf/forecasting/postprocessor.py
pyhspf/forecasting/preprocess_nrcm.py
pyhspf/preprocessing/__init__.py
pyhspf/preprocessing/cdlextractor.py
pyhspf/preprocessing/climateprocessor.py
pyhspf/preprocessing/climateutils.py
pyhspf/preprocessing/dbfutils.py
pyhspf/preprocessing/delineators.py
pyhspf/preprocessing/etcalculator.py
pyhspf/preprocessing/extract_aquifers.py
pyhspf/preprocessing/flowline.py
pyhspf/preprocessing/ftablecalculator.py
pyhspf/preprocessing/gagestation.py
pyhspf/preprocessing/ncdcstations.py
pyhspf/preprocessing/nhdplusextractor.py
pyhspf/preprocessing/nidextractor.py
pyhspf/preprocessing/nwisextractor.py
pyhspf/preprocessing/preprocessor.py
pyhspf/preprocessing/rasterutils.py
pyhspf/preprocessing/vectorutils.py
pyhspf-0.2.4.dist-info/METADATA
pyhspf-0.2.4.dist-info/WHEEL
pyhspf-0.2.4.dist-info/top_level.txt
pyhspf-0.2.4.dist-info/RECORD
