Metadata-Version: 2.1
Name: pyhspf
Version: 0.2.4
Summary: Python Extensions for utilizing the Hydrological Simulation Program in Fortran (HSPF)
Home-page: https://github.com/djlampert/PyHSPF
Author: David Lampert
Author-email: david.lampert@okstate.edu
License: 
